sqla_yaml_fixtures/__init__.py
sqla_yaml_fixtures/__main__.py
sqla_yaml_fixtures/cmd.py
sqla_yaml_fixtures-1.1.0.dist-info/AUTHORS
sqla_yaml_fixtures-1.1.0.dist-info/LICENSE
sqla_yaml_fixtures-1.1.0.dist-info/METADATA
sqla_yaml_fixtures-1.1.0.dist-info/WHEEL
sqla_yaml_fixtures-1.1.0.dist-info/top_level.txt
sqla_yaml_fixtures-1.1.0.dist-info/RECORD
