Metadata-Version: 2.1
Name: sqla-yaml-fixtures
Version: 1.1.0
Summary: Load YAML data fixtures for SQLAlchemy
Home-page: https://github.com/schettino72/sqla_yaml_fixtures
Author: Eduardo Naufel Schettino
Author-email: schettino72@gmail.com
License: MIT
Keywords: fixture,sqlalchemy
Platform: UNKNOWN
Classifier: Development Status :: 4 - Beta
Classifier: License :: OSI Approved :: MIT License
Classifier: Natural Language :: English
Classifier: Programming Language :: Python :: 3
Classifier: Programming Language :: Python :: 3.6
Classifier: Programming Language :: Python :: 3.7
Classifier: Programming Language :: Python :: 3.8
Classifier: Programming Language :: Python :: 3.9
Classifier: Intended Audience :: Developers
Requires-Dist: PyYAML
Requires-Dist: SQLAlchemy
